pyframe/__init__.py
pyframe/__main__.py
pyframe/common.py
pyframe/index/__init__.py
pyframe/index/indexer.py
pyframe/show/__init__.py
pyframe/show/app.py
pyframe/show/controller.py
pyframe/show/mqtt.py
pyframe/show/scheduler.py
pyframe/show/slideshow.py
pyframe/show/state.bak
pyframe/show/content/__init__.py
pyframe/show/content/base.py
pyframe/show/content/image.py
pyframe/show/content/pil_image.py
pyframe/show/content/video.py
repository/__init__.py
repository/common.py
repository/file.py
repository/index.py
repository/repository.py
repository/local/__init__.py
repository/local/file.py
repository/local/repository.py
repository/rclone/__init__.py
repository/rclone/file.py
repository/rclone/repository.py
repository/webdav/__init__.py
repository/webdav/file.py
repository/webdav/repository.py
01memories-0.0.32.data/data/bin/01memories
01memories-0.0.32.data/data/share/01memories/config/config-advanced.yaml
01memories-0.0.32.data/data/share/01memories/config/config-simple.yaml
01memories-0.0.32.data/data/share/01memories/config/config.yaml
01memories-0.0.32.data/data/share/01memories/examples/photos/example1.jpg
01memories-0.0.32.data/data/share/01memories/examples/photos/example2.jpg
01memories-0.0.32.data/data/share/01memories/examples/photos/example3.jpg
01memories-0.0.32.data/data/share/01memories/examples/photos/example4.jpg
01memories-0.0.32.data/data/share/01memories/examples/photos/example5.jpg
01memories-0.0.32.data/data/share/01memories/examples/photos/example6.jpg
01memories-0.0.32.data/data/share/01memories/examples/photos/example7.jpg
01memories-0.0.32.data/data/share/01memories/examples/photos/example8.jpg
01memories-0.0.32.data/data/share/01memories/examples/photos/example9.jpg
01memories-0.0.32.data/data/share/doc/01memories/Makefile
01memories-0.0.32.data/data/share/doc/01memories/make.bat
01memories-0.0.32.data/data/share/doc/01memories/images/frame/frame - front.jpg
01memories-0.0.32.data/data/share/doc/01memories/images/frame/frame - rear.jpg
01memories-0.0.32.dist-info/METADATA
01memories-0.0.32.dist-info/WHEEL
01memories-0.0.32.dist-info/licenses/LICENSE.md
01memories-0.0.32.dist-info/RECORD
